{"categories":[{"name":"Foundational & Engagement Therapies"},{"name":"Standard Talking Therapies"},{"name":"OCD & Exposure Therapies"},{"name":"Trauma Therapies"},{"name":"Psychosis & Rehabilitation Therapies"},{"name":"Personality Disorder Therapies"},{"name":"Eating Disorder Therapies"},{"name":"Family & Couple Therapies"},{"name":"Child & Adolescent Therapies"},{"name":"Substance Use Therapies"},{"name":"Group CBT"},{"name":"Group IPT"},{"name":"Self-Help & Digital Therapies"},{"name":"Community & Casework Support"},{"name":"Humanistic & Meaning-Based Therapies"},{"name":"Brain & Body Therapies"}],"tags":[{"name":"5-minute intervention"},{"name":"ACT"},{"name":"Anxiety"},{"name":"Behavioural activation"},{"name":"CBT"},{"name":"Crisis/risk"},{"name":"DBT"},{"name":"Distress tolerance"},{"name":"Eating/body image"},{"name":"Emotional regulation"},{"name":"Grief/loss"},{"name":"Group programme"},{"name":"Micro skill"},{"name":"Mood"},{"name":"Multi-session"},{"name":"Neurodevelopmental"},{"name":"Pain/somatic"},{"name":"Personality/interpersonal"},{"name":"Psychosis"},{"name":"Single session"},{"name":"Sleep"},{"name":"Substance use"},{"name":"Trauma"}],"measures":[{"name":"GAD-7","clinicalDomain":"Anxiety","whenToUse":"Consider when monitoring anxiety symptoms alongside therapy.","frequency":"As clinically indicated","reviewStatus":"needs_review"},{"name":"ISI","clinicalDomain":"Sleep","whenToUse":"Consider when monitoring sleep symptoms alongside therapy.","frequency":"As clinically indicated","reviewStatus":"needs_review"},{"name":"PCL-5","clinicalDomain":"Trauma","whenToUse":"Consider when monitoring trauma symptoms alongside therapy.","frequency":"As clinically indicated","reviewStatus":"needs_review"},{"name":"PHQ-9","clinicalDomain":"Mood","whenToUse":"Consider when monitoring mood symptoms alongside therapy.","frequency":"As clinically indicated","reviewStatus":"needs_review"}]}